tuyaface/__init__.py
tuyaface/aescipher.py
tuyaface/const.py
tuyaface/helper.py
tuyaface/tuyaclient.py
tuyaface-1.4.0.dist-info/LICENSE
tuyaface-1.4.0.dist-info/METADATA
tuyaface-1.4.0.dist-info/WHEEL
tuyaface-1.4.0.dist-info/top_level.txt
tuyaface-1.4.0.dist-info/RECORD
