Metadata-Version: 2.1
Name: tuyaface
Version: 1.4.0
Summary: Python library for local communication with Tuya devices.
Home-page: https://github.com/TradeFace/tuyaface/
Author: tradeface
Author-email: 
License: Unlicense
Keywords: home automation,tuya,api
Platform: any
Classifier: Development Status :: 5 - Production/Stable
Classifier: Intended Audience :: Developers
Classifier: Topic :: Home Automation
Classifier: License :: Public Domain
Classifier: Programming Language :: Python
Classifier: Programming Language :: Python :: 2
Classifier: Programming Language :: Python :: 3
Classifier: Programming Language :: Python :: 3.6
Requires-Dist: pycryptodomex (==3.9.7)
Requires-Dist: bitstring (==3.1.6)
